pycrosstalker/.DS_Store
pycrosstalker/__init__.py
pycrosstalker/plots/__init__.py
pycrosstalker/plots/plot.py
pycrosstalker/tools/Comparative_condition.py
pycrosstalker/tools/Single_Condition.py
pycrosstalker/tools/__init__.py
pycrosstalker/tools/generate_report.py
pycrosstalker/tools/lrobject.py
pycrosstalker/tools/utils.py
pycrosstalker-2.1.0.dist-info/LICENSE
pycrosstalker-2.1.0.dist-info/METADATA
pycrosstalker-2.1.0.dist-info/WHEEL
pycrosstalker-2.1.0.dist-info/RECORD
