Metadata-Version: 2.3
Name: pycrosstalker
Version: 2.1.0
Summary: 
License: MIT
Author: ruthvik07
Author-email: ruthvik.koppala@gmail.com
Requires-Python: >=3.11
Classifier: License :: OSI Approved :: MIT License
Classifier: Programming Language :: Python :: 3
Classifier: Programming Language :: Python :: 3.11
Classifier: Programming Language :: Python :: 3.12
Classifier: Programming Language :: Python :: 3.13
Requires-Dist: adjustText (>=1.2.0)
Requires-Dist: anndata (>=0.12.2,<0.13.0)
Requires-Dist: attrs (>=25.3.0)
Requires-Dist: gprofiler-official (==1.0.0)
Requires-Dist: igraph (>=0.11.6)
Requires-Dist: matplotlib (>=3.9.1.post1)
Requires-Dist: networkx (>=3.3)
Requires-Dist: numpy (>=1.24)
Requires-Dist: pandas (>=2.2.2)
Requires-Dist: plotly (>=6.0.1)
Requires-Dist: plotnine (>=0.13.6)
Requires-Dist: sankeyflow (>=0.4.1)
Requires-Dist: scanpy (>=1.11.4,<2.0.0)
Requires-Dist: scikit-learn (>=1.5.1)
Requires-Dist: seaborn (>=0.13.2)
Requires-Dist: tqdm (>=4.66.5)
